MANIFEST.in
README.md
setup.cfg
setup.py
easylife/__init__.py
easylife/run_tools.py
easylife/utils.py
easylife.egg-info/PKG-INFO
easylife.egg-info/SOURCES.txt
easylife.egg-info/dependency_links.txt
easylife.egg-info/entry_points.txt
easylife.egg-info/requires.txt
easylife.egg-info/top_level.txt
easylife/photo_organizer/__init__.py
easylife/photo_organizer/run_photo_organizer.py
easylife/transfers/__init__.py
easylife/transfers/run_tool.py
easylife/transfers/user_data_schema.json