Metadata-Version: 1.1
Name: easylife
Version: 0.2.0
Summary: Group of useful scripts and tools that makes your life easier by doing things for you. Automates same things you can do every day.
Home-page: https://github.com/JaniszM/easylife
Author: Janiszewski Marcin
Author-email: janiszewski.m.a@gmail.com
License: MIT
Download-URL: https://github.com/JaniszM/easylife/tarball/0.2.0
Keywords: easy,life,shorthand,quick,script,tool,useful,bill,transfer,bank,photo,organizer
Platform: UNKNOWN
Classifier: Programming Language :: Python :: 2.7
Classifier: Programming Language :: Python :: 3.0
Classifier: Development Status :: 3 - Alpha
Classifier: License :: OSI Approved :: MIT License
Classifier: Topic :: Home Automation
